deepsweepai/__init__.py
deepsweepai/adversarial.py
deepsweepai/cli.py
deepsweepai/compliance.py
deepsweepai/licensing.py
deepsweepai/plugins.py
deepsweepai/pro.py
deepsweepai/report.py
deepsweepai/scanner.py
deepsweepai/telemetry.py
deepsweepai/telemetry_event.py
deepsweepai/utils.py
deepsweepai-0.3.6.dist-info/licenses/LICENSE
deepsweepai-0.3.6.dist-info/METADATA
deepsweepai-0.3.6.dist-info/WHEEL
deepsweepai-0.3.6.dist-info/entry_points.txt
deepsweepai-0.3.6.dist-info/top_level.txt
deepsweepai-0.3.6.dist-info/RECORD
