Metadata-Version: 2.4
Name: deepsweepai
Version: 0.3.6
Summary: Independent AI agent security testing & compliance platform
Author: DeepSweep AI
License: MIT
Project-URL: Homepage, https://deepsweep.ai
Project-URL: Documentation, https://docs.deepsweep.ai
Project-URL: Repository, https://github.com/deepsweep-ai/deepsweepai
Project-URL: Bug Reports, https://github.com/deepsweep-ai/deepsweepai/issues
Project-URL: Terms of Service, https://deepsweep.ai/terms
Project-URL: Privacy Policy, https://deepsweep.ai/privacy
Keywords: ai,security,llm,agents,compliance,redteam
Classifier: Development Status :: 4 - Beta
Classifier: Intended Audience :: Developers
Classifier: License :: OSI Approved :: MIT License
Classifier: Topic :: Security
Requires-Python: >=3.9
License-File: LICENSE
Requires-Dist: rich>=13.0.0
Requires-Dist: pyyaml
Requires-Dist: requests>=2.31.0
Provides-Extra: openai
Requires-Dist: openai>=1.0.0; extra == "openai"
Provides-Extra: anthropic
Requires-Dist: anthropic>=0.30; extra == "anthropic"
Provides-Extra: google
Requires-Dist: google-generativeai>=0.6.0; extra == "google"
Dynamic: license-file
